Metadata-Version: 2.1
Name: shellbind
Version: 1.0
Summary: Shellbinding to Webshell
Home-page: https://github.com/hydr0nium/shellbind
Author: Hydr0nium/Sol
License: GPL-3.0
License-File: LICENSE
